{
  "area": 13.6752,
  "cell_footprint": "sky130_fd_sc_hvl__einvn",
  "cell_leakage_power": 0.0,
  "pg_pin,VGND": {
    "pg_type": "primary_ground",
    "related_bias_pin": "VPB",
    "voltage_name": "VGND"
  },
  "pg_pin,VNB": {
    "pg_type": "nwell",
    "physical_connection": "device_layer",
    "voltage_name": "VNB"
  },
  "pg_pin,VPB": {
    "pg_type": "pwell",
    "physical_connection": "device_layer",
    "voltage_name": "VPB"
  },
  "pg_pin,VPWR": {
    "pg_type": "primary_power",
    "related_bias_pin": "VNB",
    "voltage_name": "VPWR"
  },
  "pin,A": {
    "capacitance": 0.00442,
    "clock": "false",
    "direction": "input",
    "internal_power": {
      "fall_power,hidden_pwr_template11": {
        "index_1": [
          0.001,
          0.013,
          0.026,
          0.072,
          0.216,
          0.432,
          0.864,
          1.296,
          2.5,
          3.125,
          3.75
        ],
        "values": [
          0.00245,
          0.00232,
          0.00228,
          0.00219,
          0.00251,
          0.0025,
          0.00247,
          0.00256,
          0.00288,
          0.00303,
          0.00318
        ]
      },
      "rise_power,hidden_pwr_template11": {
        "index_1": [
          0.001,
          0.013,
          0.026,
          0.072,
          0.216,
          0.432,
          0.864,
          1.296,
          2.5,
          3.125,
          3.75
        ],
        "values": [
          0.00223,
          0.01303,
          0.00278,
          0.00139,
          0.00193,
          0.00228,
          0.00234,
          0.00254,
          0.00286,
          0.00301,
          0.00316
        ]
      }
    },
    "max_transition": 3.75,
    "related_ground_pin": "VGND",
    "related_power_pin": "VPWR"
  },
  "pin,TE_B": {
    "capacitance": 0.00496,
    "clock": "false",
    "direction": "input",
    "max_transition": 3.75,
    "related_ground_pin": "VGND",
    "related_power_pin": "VPWR"
  },
  "pin,Z": {
    "capacitance": 0.00416,
    "direction": "output",
    "function": "(!A)",
    "internal_power": [
      {
        "fall_power,pwr_template11x7": {
          "index_1": [
            0.001,
            0.013,
            0.026,
            0.072,
            0.216,
            0.432,
            0.864,
            1.296,
            2.5,
            3.125,
            3.75
          ],
          "index_2": [
            0.00416,
            0.00571,
            0.00727,
            0.01038,
            0.01661,
            0.02906,
            0.05395
          ],
          "values": [
            [
              0.00357,
              0.00154,
              -0.0006,
              -0.00481,
              -0.01331,
              -0.03026,
              -0.06414
            ],
            [
              0.00401,
              0.00166,
              -0.00045,
              -0.00478,
              -0.01331,
              -0.03028,
              -0.06411
            ],
            [
              0.00416,
              0.00175,
              -0.00046,
              -0.00474,
              -0.01327,
              -0.03027,
              -0.06418
            ],
            [
              0.00463,
              0.00205,
              -0.00029,
              -0.00471,
              -0.01332,
              -0.03034,
              -0.06427
            ],
            [
              0.00517,
              0.00261,
              0.00019,
              -0.00439,
              -0.01316,
              -0.0303,
              -0.06428
            ],
            [
              0.00548,
              0.00301,
              0.0006,
              -0.00401,
              -0.01289,
              -0.03014,
              -0.06421
            ],
            [
              0.00563,
              0.00332,
              0.001,
              -0.00356,
              -0.01248,
              -0.02985,
              -0.06404
            ],
            [
              0.00562,
              0.0034,
              0.00115,
              -0.00333,
              -0.01223,
              -0.02963,
              -0.0639
            ],
            [
              0.00542,
              0.0033,
              0.00115,
              -0.00319,
              -0.01189,
              -0.02924,
              -0.06362
            ],
            [
              0.00526,
              0.00316,
              0.00104,
              -0.00321,
              -0.01185,
              -0.02914,
              -0.06349
            ],
            [
              0.00511,
              0.00308,
              0.00089,
              -0.00326,
              -0.01186,
              -0.02907,
              -0.06339
            ]
          ]
        },
        "related_pin": "A",
        "rise_power,pwr_template11x7": {
          "index_1": [
            0.001,
            0.013,
            0.026,
            0.072,
            0.216,
            0.432,
            0.864,
            1.296,
            2.5,
            3.125,
            3.75
          ],
          "index_2": [
            0.00416,
            0.00571,
            0.00727,
            0.01038,
            0.01661,
            0.02906,
            0.05395
          ],
          "values": [
            [
              0.01184,
              0.01507,
              0.0174,
              0.0216,
              0.03001,
              0.04678,
              0.08055
            ],
            [
              0.01209,
              0.01532,
              0.01764,
              0.02186,
              0.03028,
              0.04705,
              0.08092
            ],
            [
              0.01221,
              0.01531,
              0.01763,
              0.02186,
              0.0303,
              0.04709,
              0.08086
            ],
            [
              0.01252,
              0.01522,
              0.01752,
              0.02184,
              0.03035,
              0.04712,
              0.08102
            ],
            [
              0.01236,
              0.01483,
              0.01719,
              0.02161,
              0.03017,
              0.04712,
              0.08093
            ],
            [
              0.01217,
              0.01454,
              0.01688,
              0.02135,
              0.02998,
              0.04701,
              0.08095
            ],
            [
              0.01213,
              0.01436,
              0.01661,
              0.02102,
              0.02969,
              0.04676,
              0.08073
            ],
            [
              0.01216,
              0.01434,
              0.01654,
              0.02085,
              0.02952,
              0.04665,
              0.08061
            ],
            [
              0.01232,
              0.01443,
              0.01658,
              0.02081,
              0.02931,
              0.04627,
              0.08036
            ],
            [
              0.01247,
              0.01451,
              0.01665,
              0.02088,
              0.02934,
              0.04617,
              0.08024
            ],
            [
              0.01258,
              0.01461,
              0.01672,
              0.02095,
              0.02937,
              0.0462,
              0.08028
            ]
          ]
        }
      },
      {
        "fall_power,pwr_template11x7": {
          "index_1": [
            0.001,
            0.013,
            0.026,
            0.072,
            0.216,
            0.432,
            0.864,
            1.296,
            2.5,
            3.125,
            3.75
          ],
          "index_2": [
            0.00416,
            0.00571,
            0.00727,
            0.01038,
            0.01661,
            0.02906,
            0.05395
          ],
          "values": [
            [
              0.00357,
              0.00154,
              -0.0006,
              -0.00481,
              -0.01331,
              -0.03026,
              -0.06414
            ],
            [
              0.00401,
              0.00166,
              -0.00045,
              -0.00478,
              -0.01331,
              -0.03028,
              -0.06411
            ],
            [
              0.00416,
              0.00175,
              -0.00046,
              -0.00474,
              -0.01327,
              -0.03027,
              -0.06418
            ],
            [
              0.00463,
              0.00205,
              -0.00029,
              -0.00471,
              -0.01332,
              -0.03034,
              -0.06427
            ],
            [
              0.00517,
              0.00261,
              0.00019,
              -0.00439,
              -0.01316,
              -0.0303,
              -0.06428
            ],
            [
              0.00548,
              0.00301,
              0.0006,
              -0.00401,
              -0.01289,
              -0.03014,
              -0.06421
            ],
            [
              0.00563,
              0.00332,
              0.001,
              -0.00356,
              -0.01248,
              -0.02985,
              -0.06404
            ],
            [
              0.00562,
              0.0034,
              0.00115,
              -0.00333,
              -0.01223,
              -0.02963,
              -0.0639
            ],
            [
              0.00542,
              0.0033,
              0.00115,
              -0.00319,
              -0.01189,
              -0.02924,
              -0.06362
            ],
            [
              0.00526,
              0.00316,
              0.00104,
              -0.00321,
              -0.01185,
              -0.02914,
              -0.06349
            ],
            [
              0.00511,
              0.00308,
              0.00089,
              -0.00326,
              -0.01186,
              -0.02907,
              -0.06339
            ]
          ]
        },
        "related_pin": "TE_B",
        "rise_power,pwr_template11x7": {
          "index_1": [
            0.001,
            0.013,
            0.026,
            0.072,
            0.216,
            0.432,
            0.864,
            1.296,
            2.5,
            3.125,
            3.75
          ],
          "index_2": [
            0.00416,
            0.00571,
            0.00727,
            0.01038,
            0.01661,
            0.02906,
            0.05395
          ],
          "values": [
            [
              0.01184,
              0.01507,
              0.0174,
              0.0216,
              0.03001,
              0.04678,
              0.08055
            ],
            [
              0.01209,
              0.01532,
              0.01764,
              0.02186,
              0.03028,
              0.04705,
              0.08092
            ],
            [
              0.01221,
              0.01531,
              0.01763,
              0.02186,
              0.0303,
              0.04709,
              0.08086
            ],
            [
              0.01252,
              0.01522,
              0.01752,
              0.02184,
              0.03035,
              0.04712,
              0.08102
            ],
            [
              0.01236,
              0.01483,
              0.01719,
              0.02161,
              0.03017,
              0.04712,
              0.08093
            ],
            [
              0.01217,
              0.01454,
              0.01688,
              0.02135,
              0.02998,
              0.04701,
              0.08095
            ],
            [
              0.01213,
              0.01436,
              0.01661,
              0.02102,
              0.02969,
              0.04676,
              0.08073
            ],
            [
              0.01216,
              0.01434,
              0.01654,
              0.02085,
              0.02952,
              0.04665,
              0.08061
            ],
            [
              0.01232,
              0.01443,
              0.01658,
              0.02081,
              0.02931,
              0.04627,
              0.08036
            ],
            [
              0.01247,
              0.01451,
              0.01665,
              0.02088,
              0.02934,
              0.04617,
              0.08024
            ],
            [
              0.01258,
              0.01461,
              0.01672,
              0.02095,
              0.02937,
              0.0462,
              0.08028
            ]
          ]
        }
      }
    ],
    "max_capacitance": 0.05395,
    "power_down_function": "(!VPWR + VGND)",
    "related_ground_pin": "VGND",
    "related_power_pin": "VPWR",
    "three_state": "(TE_B)",
    "timing": [
      {
        "cell_fall,delay_template11x7": {
          "index_1": [
            0.001,
            0.013,
            0.026,
            0.072,
            0.216,
            0.432,
            0.864,
            1.296,
            2.5,
            3.125,
            3.75
          ],
          "index_2": [
            0.00416,
            0.00571,
            0.00727,
            0.01038,
            0.01661,
            0.02906,
            0.05395
          ],
          "values": [
            [
              0.23127,
              0.32307,
              0.4045,
              0.56516,
              0.88589,
              1.52647,
              2.80777
            ],
            [
              0.2317,
              0.32368,
              0.40684,
              0.56858,
              0.89114,
              1.53237,
              2.81217
            ],
            [
              0.23249,
              0.32553,
              0.40988,
              0.57338,
              0.89561,
              1.53683,
              2.81833
            ],
            [
              0.23908,
              0.33483,
              0.4228,
              0.58956,
              0.91501,
              1.5587,
              2.839
            ],
            [
              0.28286,
              0.37797,
              0.46875,
              0.64068,
              0.9715,
              1.6186,
              2.9009
            ],
            [
              0.36688,
              0.4572,
              0.54677,
              0.7198,
              1.0537,
              1.7042,
              2.9917
            ],
            [
              0.4949,
              0.619,
              0.7189,
              0.8889,
              1.2233,
              1.8776,
              3.1697
            ],
            [
              0.5916,
              0.7454,
              0.8682,
              1.0659,
              1.398,
              2.0543,
              3.3462
            ],
            [
              0.79177,
              1.01077,
              1.18507,
              1.46327,
              1.88727,
              2.55197,
              3.83987
            ],
            [
              0.87433,
              1.12123,
              1.31783,
              1.63093,
              2.10893,
              2.81463,
              4.10513
            ],
            [
              0.9482,
              1.22,
              1.4369,
              1.7835,
              2.3091,
              3.0781,
              4.3686
            ]
          ]
        },
        "cell_rise,delay_template11x7": {
          "index_1": [
            0.001,
            0.013,
            0.026,
            0.072,
            0.216,
            0.432,
            0.864,
            1.296,
            2.5,
            3.125,
            3.75
          ],
          "index_2": [
            0.00416,
            0.00571,
            0.00727,
            0.01038,
            0.01661,
            0.02906,
            0.05395
          ],
          "values": [
            [
              0.18808,
              0.30957,
              0.39842,
              0.5616,
              0.88656,
              1.53407,
              2.82787
            ],
            [
              0.19253,
              0.31256,
              0.40225,
              0.56666,
              0.89188,
              1.53897,
              2.83687
            ],
            [
              0.19861,
              0.31608,
              0.40495,
              0.57011,
              0.89599,
              1.54473,
              2.83803
            ],
            [
              0.22305,
              0.32628,
              0.41508,
              0.58251,
              0.91001,
              1.559,
              2.8575
            ],
            [
              0.27152,
              0.36643,
              0.45654,
              0.62734,
              0.9597,
              1.6123,
              2.9074
            ],
            [
              0.35231,
              0.4427,
              0.53148,
              0.7038,
              1.0386,
              1.6944,
              2.9946
            ],
            [
              0.4633,
              0.5919,
              0.6957,
              0.8669,
              1.2027,
              1.8598,
              3.1606
            ],
            [
              0.5446,
              0.7034,
              0.8299,
              1.0339,
              1.3704,
              2.0294,
              3.3308
            ],
            [
              0.70327,
              0.92767,
              1.10657,
              1.39247,
              1.82927,
              2.50607,
              3.80857
            ],
            [
              0.76453,
              1.01703,
              1.21833,
              1.54043,
              2.03043,
              2.75613,
              4.05953
            ],
            [
              0.8172,
              1.0951,
              1.3166,
              1.6714,
              2.2109,
              3.0039,
              4.3115
            ]
          ]
        },
        "fall_transition,delay_template11x7": {
          "index_1": [
            0.001,
            0.013,
            0.026,
            0.072,
            0.216,
            0.432,
            0.864,
            1.296,
            2.5,
            3.125,
            3.75
          ],
          "index_2": [
            0.00416,
            0.00571,
            0.00727,
            0.01038,
            0.01661,
            0.02906,
            0.05395
          ],
          "values": [
            [
              0.15551,
              0.26321,
              0.37117,
              0.58546,
              1.01595,
              1.87294,
              3.5866
            ],
            [
              0.15552,
              0.26285,
              0.37125,
              0.58638,
              1.01542,
              1.87379,
              3.5879
            ],
            [
              0.15554,
              0.263,
              0.37085,
              0.5858,
              1.01606,
              1.87409,
              3.5878
            ],
            [
              0.1554,
              0.2628,
              0.37104,
              0.58637,
              1.01604,
              1.87203,
              3.5879
            ],
            [
              0.15503,
              0.26273,
              0.37073,
              0.58593,
              1.01613,
              1.87406,
              3.5881
            ],
            [
              0.17337,
              0.26483,
              0.37035,
              0.58535,
              1.01591,
              1.8737,
              3.5869
            ],
            [
              0.257,
              0.3377,
              0.416,
              0.5992,
              1.0143,
              1.8742,
              3.5878
            ],
            [
              0.3223,
              0.4243,
              0.5071,
              0.6601,
              1.0318,
              1.8725,
              3.587
            ],
            [
              0.4762,
              0.6177,
              0.729,
              0.9117,
              1.2156,
              1.9301,
              3.587
            ],
            [
              0.5447,
              0.7052,
              0.8292,
              1.0319,
              1.3487,
              2.0078,
              3.5892
            ],
            [
              0.608,
              0.7857,
              0.9223,
              1.1427,
              1.4867,
              2.1064,
              3.6228
            ]
          ]
        },
        "related_pin": "A",
        "rise_transition,delay_template11x7": {
          "index_1": [
            0.001,
            0.013,
            0.026,
            0.072,
            0.216,
            0.432,
            0.864,
            1.296,
            2.5,
            3.125,
            3.75
          ],
          "index_2": [
            0.00416,
            0.00571,
            0.00727,
            0.01038,
            0.01661,
            0.02906,
            0.05395
          ],
          "values": [
            [
              0.17768,
              0.28872,
              0.40028,
              0.6216,
              1.06355,
              1.94719,
              3.7116
            ],
            [
              0.17763,
              0.28895,
              0.40046,
              0.62154,
              1.06398,
              1.94695,
              3.7066
            ],
            [
              0.17758,
              0.28884,
              0.39981,
              0.62158,
              1.06285,
              1.94566,
              3.7116
            ],
            [
              0.17759,
              0.28899,
              0.40028,
              0.62156,
              1.06384,
              1.94666,
              3.7061
            ],
            [
              0.17672,
              0.28838,
              0.40035,
              0.62148,
              1.06243,
              1.94635,
              3.7116
            ],
            [
              0.20041,
              0.29324,
              0.39934,
              0.62113,
              1.06262,
              1.9453,
              3.7066
            ],
            [
              0.2803,
              0.374,
              0.4547,
              0.6402,
              1.0624,
              1.9466,
              3.7113
            ],
            [
              0.3359,
              0.4528,
              0.5492,
              0.7088,
              1.087,
              1.9446,
              3.7115
            ],
            [
              0.481,
              0.6288,
              0.7504,
              0.9535,
              1.285,
              2.0157,
              3.7114
            ],
            [
              0.5468,
              0.7112,
              0.8441,
              1.0635,
              1.4181,
              2.0983,
              3.7218
            ],
            [
              0.6093,
              0.7882,
              0.9328,
              1.1678,
              1.5493,
              2.2063,
              3.7532
            ]
          ]
        },
        "timing_sense": "negative_unate"
      },
      {
        "cell_fall,delay_template11x7": {
          "index_1": [
            0.001,
            0.013,
            0.026,
            0.072,
            0.216,
            0.432,
            0.864,
            1.296,
            2.5,
            3.125,
            3.75
          ],
          "index_2": [
            0.00416,
            0.00571,
            0.00727,
            0.01038,
            0.01661,
            0.02906,
            0.05395
          ],
          "values": [
            [
              0.51426,
              0.60012,
              0.68318,
              0.84484,
              1.16547,
              1.80607,
              3.08277
            ],
            [
              0.51908,
              0.60504,
              0.68806,
              0.84991,
              1.17057,
              1.81087,
              3.08877
            ],
            [
              0.52439,
              0.61025,
              0.693,
              0.85465,
              1.17533,
              1.81553,
              3.09593
            ],
            [
              0.54113,
              0.627,
              0.71006,
              0.87174,
              1.1929,
              1.8329,
              3.1103
            ],
            [
              0.59883,
              0.68465,
              0.76785,
              0.9297,
              1.2505,
              1.89,
              3.1705
            ],
            [
              0.6927,
              0.7785,
              0.8617,
              1.0236,
              1.3443,
              1.9841,
              3.2642
            ],
            [
              0.8753,
              0.9618,
              1.0451,
              1.2071,
              1.5274,
              2.168,
              3.4463
            ],
            [
              1.0194,
              1.1088,
              1.1939,
              1.3569,
              1.6783,
              2.3176,
              3.5988
            ],
            [
              1.31337,
              1.40807,
              1.49627,
              1.66367,
              1.98897,
              2.63117,
              3.91127
            ],
            [
              1.43283,
              1.52993,
              1.61983,
              1.78873,
              2.11543,
              2.75873,
              4.03863
            ],
            [
              1.5381,
              1.6378,
              1.7289,
              1.8995,
              2.2266,
              2.8723,
              4.1518
            ]
          ]
        },
        "cell_rise,delay_template11x7": {
          "index_1": [
            0.001,
            0.013,
            0.026,
            0.072,
            0.216,
            0.432,
            0.864,
            1.296,
            2.5,
            3.125,
            3.75
          ],
          "index_2": [
            0.00416,
            0.00571,
            0.00727,
            0.01038,
            0.01661,
            0.02906,
            0.05395
          ],
          "values": [
            [
              0.22283,
              0.30455,
              0.38611,
              0.54829,
              0.87238,
              1.52087,
              2.81157
            ],
            [
              0.22805,
              0.30974,
              0.39132,
              0.55345,
              0.87758,
              1.52567,
              2.81717
            ],
            [
              0.23412,
              0.31588,
              0.3974,
              0.55954,
              0.88326,
              1.53093,
              2.82513
            ],
            [
              0.2559,
              0.33758,
              0.41915,
              0.58136,
              0.9051,
              1.5535,
              2.846
            ],
            [
              0.32372,
              0.40541,
              0.48698,
              0.64916,
              0.973,
              1.6216,
              2.9135
            ],
            [
              0.41433,
              0.49674,
              0.57836,
              0.7406,
              1.0646,
              1.7128,
              3.0046
            ],
            [
              0.5474,
              0.6474,
              0.738,
              0.902,
              1.226,
              1.8745,
              3.1661
            ],
            [
              0.6499,
              0.7649,
              0.8678,
              1.0517,
              1.3801,
              2.0286,
              3.3226
            ],
            [
              0.85977,
              1.01727,
              1.15167,
              1.38367,
              1.77767,
              2.44827,
              3.74277
            ],
            [
              0.94073,
              1.12073,
              1.27163,
              1.52743,
              1.95423,
              2.66473,
              3.96083
            ],
            [
              1.0088,
              1.2107,
              1.3783,
              1.658,
              2.1165,
              2.87,
              4.179
            ]
          ]
        },
        "fall_transition,delay_template11x7": {
          "index_1": [
            0.001,
            0.013,
            0.026,
            0.072,
            0.216,
            0.432,
            0.864,
            1.296,
            2.5,
            3.125,
            3.75
          ],
          "index_2": [
            0.00416,
            0.00571,
            0.00727,
            0.01038,
            0.01661,
            0.02906,
            0.05395
          ],
          "values": [
            [
              0.17559,
              0.27859,
              0.3824,
              0.5913,
              1.01602,
              1.86933,
              3.5805
            ],
            [
              0.17555,
              0.27872,
              0.38234,
              0.59133,
              1.01545,
              1.86798,
              3.581
            ],
            [
              0.17563,
              0.27868,
              0.38236,
              0.59112,
              1.01582,
              1.87,
              3.5772
            ],
            [
              0.17558,
              0.27858,
              0.3824,
              0.59136,
              1.01529,
              1.8691,
              3.5808
            ],
            [
              0.17556,
              0.27871,
              0.38254,
              0.59149,
              1.01505,
              1.8697,
              3.5792
            ],
            [
              0.17553,
              0.2787,
              0.3825,
              0.5915,
              1.0151,
              1.8693,
              3.5796
            ],
            [
              0.1777,
              0.2797,
              0.3835,
              0.5922,
              1.0158,
              1.8687,
              3.581
            ],
            [
              0.1856,
              0.2875,
              0.3897,
              0.5954,
              1.0172,
              1.8703,
              3.5764
            ],
            [
              0.1998,
              0.3013,
              0.4034,
              0.6087,
              1.027,
              1.8747,
              3.5773
            ],
            [
              0.207,
              0.3083,
              0.4092,
              0.6126,
              1.0299,
              1.8763,
              3.5814
            ],
            [
              0.2141,
              0.3147,
              0.4154,
              0.6172,
              1.0327,
              1.8797,
              3.585
            ]
          ]
        },
        "related_pin": "TE_B",
        "rise_transition,delay_template11x7": {
          "index_1": [
            0.001,
            0.013,
            0.026,
            0.072,
            0.216,
            0.432,
            0.864,
            1.296,
            2.5,
            3.125,
            3.75
          ],
          "index_2": [
            0.00416,
            0.00571,
            0.00727,
            0.01038,
            0.01661,
            0.02906,
            0.05395
          ],
          "values": [
            [
              0.18094,
              0.29039,
              0.4005,
              0.62078,
              1.06142,
              1.94365,
              3.7051
            ],
            [
              0.18094,
              0.29056,
              0.40016,
              0.62073,
              1.0617,
              1.94036,
              3.7012
            ],
            [
              0.18093,
              0.2904,
              0.4003,
              0.62031,
              1.06058,
              1.94342,
              3.7031
            ],
            [
              0.18085,
              0.28983,
              0.40092,
              0.62067,
              1.0619,
              1.94085,
              3.705
            ],
            [
              0.1809,
              0.29047,
              0.40093,
              0.62084,
              1.06179,
              1.94318,
              3.7041
            ],
            [
              0.18927,
              0.29331,
              0.40135,
              0.62018,
              1.06134,
              1.9412,
              3.7046
            ],
            [
              0.2345,
              0.3312,
              0.4308,
              0.6343,
              1.0626,
              1.9422,
              3.7051
            ],
            [
              0.2751,
              0.3831,
              0.4817,
              0.6737,
              1.0808,
              1.9408,
              3.7024
            ],
            [
              0.3871,
              0.5103,
              0.6235,
              0.8296,
              1.206,
              1.9978,
              3.7038
            ],
            [
              0.4448,
              0.576,
              0.694,
              0.9066,
              1.2932,
              2.056,
              3.7215
            ],
            [
              0.5024,
              0.6405,
              0.7635,
              0.9839,
              1.3815,
              2.1261,
              3.7519
            ]
          ]
        },
        "timing_sense": "negative_unate",
        "timing_type": "three_state_enable"
      },
      {
        "cell_fall,delay_template11x7": {
          "index_1": [
            0.001,
            0.013,
            0.026,
            0.072,
            0.216,
            0.432,
            0.864,
            1.296,
            2.5,
            3.125,
            3.75
          ],
          "index_2": [
            0.00416,
            0.00571,
            0.00727,
            0.01038,
            0.01661,
            0.02906,
            0.05395
          ],
          "values": [
            [
              5e-05,
              5e-05,
              5e-05,
              5e-05,
              5e-05,
              5e-05,
              5e-05
            ],
            [
              0.38477,
              0.38477,
              0.38477,
              0.38477,
              0.38477,
              0.38477,
              0.38477
            ],
            [
              0.57565,
              0.57565,
              0.57565,
              0.57565,
              0.57565,
              0.57565,
              0.57565
            ],
            [
              0.66305,
              0.66305,
              0.66305,
              0.66305,
              0.66305,
              0.66305,
              0.66305
            ],
            [
              0.75135,
              0.75135,
              0.75135,
              0.75135,
              0.75135,
              0.75135,
              0.75135
            ],
            [
              0.855,
              0.855,
              0.855,
              0.855,
              0.855,
              0.855,
              0.855
            ],
            [
              1.0949,
              1.0949,
              1.0949,
              1.0949,
              1.0949,
              1.0949,
              1.0949
            ],
            [
              1.3587,
              1.3587,
              1.3587,
              1.3587,
              1.3587,
              1.3587,
              1.3587
            ],
            [
              2.12927,
              2.12927,
              2.12927,
              2.12927,
              2.12927,
              2.12927,
              2.12927
            ],
            [
              1.88243,
              1.88243,
              1.88243,
              1.88243,
              1.88243,
              1.88243,
              1.88243
            ],
            [
              1.8973,
              1.8973,
              1.8973,
              1.8973,
              1.8973,
              1.8973,
              1.8973
            ]
          ]
        },
        "cell_rise,delay_template11x7": {
          "index_1": [
            0.001,
            0.013,
            0.026,
            0.072,
            0.216,
            0.432,
            0.864,
            1.296,
            2.5,
            3.125,
            3.75
          ],
          "index_2": [
            0.00416,
            0.00571,
            0.00727,
            0.01038,
            0.01661,
            0.02906,
            0.05395
          ],
          "values": [
            [
              -0.00066,
              -0.00066,
              -0.00066,
              -0.00066,
              -0.00066,
              -0.00066,
              -0.00066
            ],
            [
              0.70595,
              0.70595,
              0.70595,
              0.70595,
              0.70595,
              0.70595,
              0.70595
            ],
            [
              0.6014,
              0.6014,
              0.6014,
              0.6014,
              0.6014,
              0.6014,
              0.6014
            ],
            [
              0.77935,
              0.77935,
              0.77935,
              0.77935,
              0.77935,
              0.77935,
              0.77935
            ],
            [
              0.9068,
              0.9068,
              0.9068,
              0.9068,
              0.9068,
              0.9068,
              0.9068
            ],
            [
              1.0162,
              1.0162,
              1.0162,
              1.0162,
              1.0162,
              1.0162,
              1.0162
            ],
            [
              1.2131,
              1.2131,
              1.2131,
              1.2131,
              1.2131,
              1.2131,
              1.2131
            ],
            [
              1.4067,
              1.4067,
              1.4067,
              1.4067,
              1.4067,
              1.4067,
              1.4067
            ],
            [
              1.81567,
              1.81567,
              1.81567,
              1.81567,
              1.81567,
              1.81567,
              1.81567
            ],
            [
              1.98733,
              1.98733,
              1.98733,
              1.98733,
              1.98733,
              1.98733,
              1.98733
            ],
            [
              2.1319,
              2.1319,
              2.1319,
              2.1319,
              2.1319,
              2.1319,
              2.1319
            ]
          ]
        },
        "fall_transition,delay_template11x7": {
          "index_1": [
            0.001,
            0.013,
            0.026,
            0.072,
            0.216,
            0.432,
            0.864,
            1.296,
            2.5,
            3.125,
            3.75
          ],
          "index_2": [
            0.00416,
            0.00571,
            0.00727,
            0.01038,
            0.01661,
            0.02906,
            0.05395
          ],
          "values": [
            [
              0.0,
              0.0,
              0.0,
              0.0,
              0.0,
              0.0,
              0.0
            ],
            [
              0.0,
              0.0,
              0.0,
              0.0,
              0.0,
              0.0,
              0.0
            ],
            [
              0.0,
              0.0,
              0.0,
              0.0,
              0.0,
              0.0,
              0.0
            ],
            [
              0.0,
              0.0,
              0.0,
              0.0,
              0.0,
              0.0,
              0.0
            ],
            [
              0.0,
              0.0,
              0.0,
              0.0,
              0.0,
              0.0,
              0.0
            ],
            [
              0.0,
              0.0,
              0.0,
              0.0,
              0.0,
              0.0,
              0.0
            ],
            [
              0.0,
              0.0,
              0.0,
              0.0,
              0.0,
              0.0,
              0.0
            ],
            [
              0.0,
              0.0,
              0.0,
              0.0,
              0.0,
              0.0,
              0.0
            ],
            [
              0.0,
              0.0,
              0.0,
              0.0,
              0.0,
              0.0,
              0.0
            ],
            [
              0.0,
              0.0,
              0.0,
              0.0,
              0.0,
              0.0,
              0.0
            ],
            [
              0.0,
              0.0,
              0.0,
              0.0,
              0.0,
              0.0,
              0.0
            ]
          ]
        },
        "related_pin": "TE_B",
        "rise_transition,delay_template11x7": {
          "index_1": [
            0.001,
            0.013,
            0.026,
            0.072,
            0.216,
            0.432,
            0.864,
            1.296,
            2.5,
            3.125,
            3.75
          ],
          "index_2": [
            0.00416,
            0.00571,
            0.00727,
            0.01038,
            0.01661,
            0.02906,
            0.05395
          ],
          "values": [
            [
              0.0,
              0.0,
              0.0,
              0.0,
              0.0,
              0.0,
              0.0
            ],
            [
              0.0,
              0.0,
              0.0,
              0.0,
              0.0,
              0.0,
              0.0
            ],
            [
              0.0,
              0.0,
              0.0,
              0.0,
              0.0,
              0.0,
              0.0
            ],
            [
              0.0,
              0.0,
              0.0,
              0.0,
              0.0,
              0.0,
              0.0
            ],
            [
              0.0,
              0.0,
              0.0,
              0.0,
              0.0,
              0.0,
              0.0
            ],
            [
              0.0,
              0.0,
              0.0,
              0.0,
              0.0,
              0.0,
              0.0
            ],
            [
              0.0,
              0.0,
              0.0,
              0.0,
              0.0,
              0.0,
              0.0
            ],
            [
              0.0,
              0.0,
              0.0,
              0.0,
              0.0,
              0.0,
              0.0
            ],
            [
              0.0,
              0.0,
              0.0,
              0.0,
              0.0,
              0.0,
              0.0
            ],
            [
              0.0,
              0.0,
              0.0,
              0.0,
              0.0,
              0.0,
              0.0
            ],
            [
              0.0,
              0.0,
              0.0,
              0.0,
              0.0,
              0.0,
              0.0
            ]
          ]
        },
        "timing_sense": "positive_unate",
        "timing_type": "three_state_disable"
      }
    ]
  }
}