{
  "area": 5.8608,
  "cell_footprint": "sky130_fd_sc_hvl__inv",
  "cell_leakage_power": 0.8850434,
  "driver_waveform_fall": "ramp",
  "driver_waveform_rise": "ramp",
  "leakage_power": [
    {
      "value": 1.0434806,
      "when": "A"
    },
    {
      "value": 0.7266062,
      "when": "!A"
    }
  ],
  "pg_pin,VGND": {
    "pg_type": "primary_ground",
    "related_bias_pin": "VPB",
    "voltage_name": "VGND"
  },
  "pg_pin,VNB": {
    "pg_type": "nwell",
    "physical_connection": "device_layer",
    "voltage_name": "VNB"
  },
  "pg_pin,VPB": {
    "pg_type": "pwell",
    "physical_connection": "device_layer",
    "voltage_name": "VPB"
  },
  "pg_pin,VPWR": {
    "pg_type": "primary_power",
    "related_bias_pin": "VNB",
    "voltage_name": "VPWR"
  },
  "pin,A": {
    "capacitance": 0.003889,
    "clock": "false",
    "direction": "input",
    "fall_capacitance": 0.003773,
    "max_transition": 3.75,
    "related_ground_pin": "VGND",
    "related_power_pin": "VPWR",
    "rise_capacitance": 0.004004
  },
  "pin,Y": {
    "direction": "output",
    "function": "(!A)",
    "internal_power": {
      "fall_power,pwr_template11x25": {
        "index_1": [
          0.001,
          0.013,
          0.026,
          0.072,
          0.216,
          0.432,
          0.864,
          1.296,
          2.5,
          3.125,
          3.75
        ],
        "index_2": [
          0,
          0.00986,
          0.01183,
          0.0142,
          0.01704,
          0.02045,
          0.02454,
          0.02945,
          0.03534,
          0.04241,
          0.05089,
          0.06107,
          0.07329,
          0.08795,
          0.10554,
          0.12665,
          0.15198,
          0.18238,
          0.21885,
          0.26262,
          0.31514,
          0.37817,
          0.4538,
          0.54456,
          0.65347
        ],
        "values": [
          [
            -0.0437163,
            -0.1691603,
            -0.1988441,
            -0.2345866,
            -0.2774126,
            -0.3289174,
            -0.3907355,
            -0.4649383,
            -0.5538534,
            -0.6609155,
            -0.7890644,
            -0.9432088,
            -1.1275909,
            -1.3496943,
            -1.6153943,
            -1.9347327,
            -2.3180695,
            -2.7776883,
            -3.3295613,
            -3.9915927,
            -4.7857476,
            -5.7388719,
            -6.8831221,
            -8.2553333,
            -9.9031981
          ],
          [
            -0.0326244,
            -0.1722716,
            -0.2015331,
            -0.2369318,
            -0.2794147,
            -0.3305111,
            -0.3922915,
            -0.4661789,
            -0.5550707,
            -0.6619196,
            -0.7898998,
            -0.9437045,
            -1.1284067,
            -1.3500055,
            -1.6159597,
            -1.935154,
            -2.3181905,
            -2.7779828,
            -3.3295418,
            -3.9915385,
            -4.7858196,
            -5.7391014,
            -6.8830306,
            -8.2558053,
            -9.902976
          ],
          [
            -0.030263,
            -0.1736732,
            -0.2029025,
            -0.2382036,
            -0.2806653,
            -0.3318076,
            -0.393136,
            -0.4670749,
            -0.5558058,
            -0.6623157,
            -0.7904122,
            -0.9441165,
            -1.1287531,
            -1.350304,
            -1.6162182,
            -1.9353967,
            -2.3184201,
            -2.7781032,
            -3.3296907,
            -3.9916321,
            -4.786023,
            -5.7392709,
            -6.883097,
            -8.2557844,
            -9.9031963
          ],
          [
            -0.0086286,
            -0.1661752,
            -0.1953179,
            -0.2316111,
            -0.2750219,
            -0.3271019,
            -0.389389,
            -0.4641336,
            -0.5536856,
            -0.6610221,
            -0.7894088,
            -0.943158,
            -1.1277913,
            -1.3495071,
            -1.6156369,
            -1.9349414,
            -2.3180688,
            -2.7778974,
            -3.3294948,
            -3.9914536,
            -4.7857698,
            -5.7389622,
            -6.8828585,
            -8.2556058,
            -9.9028625
          ],
          [
            0.0805191,
            -0.1069537,
            -0.1401149,
            -0.17979,
            -0.2267374,
            -0.2826578,
            -0.3477493,
            -0.425409,
            -0.5186854,
            -0.6283604,
            -0.7596679,
            -0.9165611,
            -1.1033057,
            -1.3265591,
            -1.5966736,
            -1.9178335,
            -2.3033823,
            -2.7656829,
            -3.3186425,
            -3.9827714,
            -4.7786016,
            -5.7335477,
            -6.8781336,
            -8.2516958,
            -9.8995344
          ],
          [
            0.2235584,
            0.0133737,
            -0.0242818,
            -0.0686221,
            -0.1205971,
            -0.1811046,
            -0.2516941,
            -0.335167,
            -0.4338334,
            -0.5515657,
            -0.688288,
            -0.8503446,
            -1.0446698,
            -1.2754202,
            -1.5509955,
            -1.8778755,
            -2.270583,
            -2.7361203,
            -3.2929169,
            -3.9597899,
            -4.7583055,
            -5.7153576,
            -6.8623578,
            -8.2389717,
            -9.8891992
          ],
          [
            0.5121471,
            0.2834496,
            0.2421155,
            0.192966,
            0.1351658,
            0.0670271,
            -0.0128573,
            -0.1053452,
            -0.2133228,
            -0.3401568,
            -0.4886101,
            -0.6642919,
            -0.8700352,
            -1.1116086,
            -1.3987479,
            -1.736552,
            -2.1399565,
            -2.6190214,
            -3.1842156,
            -3.8597934,
            -4.6682953,
            -5.6355988,
            -6.7917514,
            -8.1749695,
            -9.8340561
          ],
          [
            0.8016327,
            0.5621271,
            0.5177693,
            0.463567,
            0.4023426,
            0.3306727,
            0.2464799,
            0.1477326,
            0.0313355,
            -0.1042988,
            -0.2601994,
            -0.4432278,
            -0.660262,
            -0.9132127,
            -1.2112525,
            -1.5602598,
            -1.9753446,
            -2.4660043,
            -3.0485781,
            -3.7377815,
            -4.560513,
            -5.5356209,
            -6.7012607,
            -8.0953841,
            -9.7615771
          ],
          [
            1.6105473,
            1.3552441,
            1.3076568,
            1.24876,
            1.1813232,
            1.1024795,
            1.0096271,
            0.9011034,
            0.7739983,
            0.6255987,
            0.4517232,
            0.2484448,
            0.0094351,
            -0.2676486,
            -0.5936244,
            -0.9730472,
            -1.4201839,
            -1.9434626,
            -2.558093,
            -3.281501,
            -4.1378169,
            -5.1543479,
            -6.3552367,
            -7.7869651,
            -9.4805493
          ],
          [
            2.0314268,
            1.76932,
            1.7176105,
            1.6613978,
            1.590829,
            1.5108553,
            1.4142799,
            1.3033808,
            1.172353,
            1.0184159,
            0.8396693,
            0.6294235,
            0.3829116,
            0.0941389,
            -0.241636,
            -0.6335447,
            -1.0919197,
            -1.629412,
            -2.2616713,
            -3.0039646,
            -3.874982,
            -4.908931,
            -6.1294912,
            -7.5787025,
            -9.2911969
          ],
          [
            2.4506597,
            2.1830426,
            2.134854,
            2.0739558,
            2.0013113,
            1.9209524,
            1.8248979,
            1.710739,
            1.5746805,
            1.4175339,
            1.2330974,
            1.0172893,
            0.7652431,
            0.4700432,
            0.1240605,
            -0.2789428,
            -0.7499292,
            -1.3008251,
            -1.9443315,
            -2.7025587,
            -3.5928754,
            -4.6413613,
            -5.879682,
            -7.3446472,
            -9.0883771
          ]
        ]
      },
      "related_pin": "A",
      "rise_power,pwr_template11x25": {
        "index_1": [
          0.001,
          0.013,
          0.026,
          0.072,
          0.216,
          0.432,
          0.864,
          1.296,
          2.5,
          3.125,
          3.75
        ],
        "index_2": [
          0,
          0.00986,
          0.01183,
          0.0142,
          0.01704,
          0.02045,
          0.02454,
          0.02945,
          0.03534,
          0.04241,
          0.05089,
          0.06107,
          0.07329,
          0.08795,
          0.10554,
          0.12665,
          0.15198,
          0.18238,
          0.21885,
          0.26262,
          0.31514,
          0.37817,
          0.4538,
          0.54456,
          0.65347
        ],
        "values": [
          [
            0.0955384,
            0.2675841,
            0.2971432,
            0.333889,
            0.3761453,
            0.4270162,
            0.4867997,
            0.5597465,
            0.6517541,
            0.7530535,
            0.8842945,
            1.0368573,
            1.2156505,
            1.4366169,
            1.704884,
            2.0187655,
            2.3965223,
            2.8568019,
            3.4050051,
            4.0521621,
            4.836092,
            5.7835499,
            6.915723,
            8.2726153,
            9.9069532
          ],
          [
            0.1074462,
            0.2643223,
            0.2943285,
            0.3308474,
            0.3727411,
            0.424678,
            0.4858072,
            0.560317,
            0.650371,
            0.7560352,
            0.8820655,
            1.0326683,
            1.2174246,
            1.4412069,
            1.7016096,
            2.0174165,
            2.4000815,
            2.8577955,
            3.3986316,
            4.0511086,
            4.8426215,
            5.7830893,
            6.9107733,
            8.2687148,
            9.9037242
          ],
          [
            0.111985,
            0.264286,
            0.2938509,
            0.3293097,
            0.3726363,
            0.4242067,
            0.4872779,
            0.5606879,
            0.6481752,
            0.7526129,
            0.8818641,
            1.0347974,
            1.22081,
            1.4407346,
            1.7041916,
            2.0184803,
            2.3976243,
            2.8566345,
            3.4016001,
            4.0523233,
            4.8431028,
            5.7844961,
            6.9117083,
            8.274892,
            9.8998088
          ],
          [
            0.1378902,
            0.2728874,
            0.3022216,
            0.3364842,
            0.378205,
            0.4293538,
            0.4882061,
            0.5637693,
            0.6500829,
            0.7567994,
            0.8840542,
            1.0349459,
            1.2191252,
            1.4403974,
            1.7052892,
            2.0190669,
            2.3970008,
            2.8579535,
            3.4008611,
            4.0556097,
            4.8434853,
            5.7785568,
            6.9154705,
            8.2725033,
            9.9064492
          ],
          [
            0.2300894,
            0.342953,
            0.3682471,
            0.3996768,
            0.4374771,
            0.4837504,
            0.5398029,
            0.607419,
            0.6916561,
            0.7920689,
            0.9163432,
            1.065338,
            1.2427472,
            1.4605274,
            1.7173457,
            2.0312807,
            2.4120888,
            2.8678096,
            3.4149619,
            4.0635866,
            4.8502293,
            5.7845548,
            6.9172948,
            8.2728891,
            9.9042902
          ],
          [
            0.3740455,
            0.4680834,
            0.4918681,
            0.5176102,
            0.5514645,
            0.5918264,
            0.6440038,
            0.7072179,
            0.7862602,
            0.8813843,
            0.9998537,
            1.1439408,
            1.3160926,
            1.5259808,
            1.7761118,
            2.0853349,
            2.4548413,
            2.9062497,
            3.4419364,
            4.0959412,
            4.8749884,
            5.814548,
            6.9398829,
            8.2946536,
            9.9237892
          ],
          [
            0.6572795,
            0.7390845,
            0.7580226,
            0.7830234,
            0.8134863,
            0.8506428,
            0.8946356,
            0.951959,
            1.0231692,
            1.113688,
            1.2192665,
            1.3513931,
            1.5120532,
            1.7116668,
            1.9558598,
            2.2484767,
            2.6052969,
            3.0460727,
            3.5634481,
            4.201833,
            4.972079,
            5.898391,
            7.0113148,
            8.3610367,
            9.9775686
          ],
          [
            0.9493611,
            1.0203499,
            1.0392031,
            1.0613299,
            1.0853381,
            1.117217,
            1.1580902,
            1.2120637,
            1.2764737,
            1.3582481,
            1.4592655,
            1.5825748,
            1.7371843,
            1.9227758,
            2.1488599,
            2.4303042,
            2.777482,
            3.2053851,
            3.7243512,
            4.3570885,
            5.1099171,
            6.0207588,
            7.1215412,
            8.4610507,
            10.0678674
          ],
          [
            1.7587868,
            1.8207983,
            1.8352629,
            1.8545987,
            1.875536,
            1.9035826,
            1.9362836,
            1.9797783,
            2.0369308,
            2.1018743,
            2.1888291,
            2.2965837,
            2.4347144,
            2.6031386,
            2.8125278,
            3.0717571,
            3.3917049,
            3.7896069,
            4.2638713,
            4.855281,
            5.5843357,
            6.4592405,
            7.534107,
            8.836231,
            10.4087183
          ],
          [
            2.1799361,
            2.2366933,
            2.2481546,
            2.2666125,
            2.2905046,
            2.3158784,
            2.3481889,
            2.3911444,
            2.4421929,
            2.5066778,
            2.5888001,
            2.6887698,
            2.8175981,
            2.9785627,
            3.1830588,
            3.4324479,
            3.7429423,
            4.1257144,
            4.5904257,
            5.1600751,
            5.8642976,
            6.7323719,
            7.7838544,
            9.0697701,
            10.6247662
          ],
          [
            2.5969154,
            2.6551563,
            2.6692369,
            2.6870909,
            2.7039843,
            2.7302606,
            2.7638496,
            2.8035119,
            2.8543275,
            2.9156903,
            2.9930725,
            3.0889263,
            3.2049384,
            3.35917,
            3.5573174,
            3.801639,
            4.098709,
            4.4702736,
            4.9270091,
            5.4871478,
            6.1739818,
            7.0190746,
            8.0592185,
            9.3163386,
            10.8613306
          ]
        ]
      }
    },
    "max_capacitance": 0.517283,
    "max_transition": 4.559583,
    "power_down_function": "(!VPWR + VGND)",
    "related_ground_pin": "VGND",
    "related_power_pin": "VPWR",
    "timing": {
      "cell_fall,delay_template11x25": {
        "index_1": [
          0.001,
          0.013,
          0.026,
          0.072,
          0.216,
          0.432,
          0.864,
          1.296,
          2.5,
          3.125,
          3.75
        ],
        "index_2": [
          0,
          0.00986,
          0.01183,
          0.0142,
          0.01704,
          0.02045,
          0.02454,
          0.02945,
          0.03534,
          0.04241,
          0.05089,
          0.06107,
          0.07329,
          0.08795,
          0.10554,
          0.12665,
          0.15198,
          0.18238,
          0.21885,
          0.26262,
          0.31514,
          0.37817,
          0.4538,
          0.54456,
          0.65347
        ],
        "values": [
          [
            0.0166739,
            0.076035,
            0.0862278,
            0.0988248,
            0.1134403,
            0.1309741,
            0.1527481,
            0.178586,
            0.2088691,
            0.2454821,
            0.2887905,
            0.341331,
            0.4063043,
            0.4806016,
            0.5715261,
            0.6807738,
            0.8114704,
            0.969151,
            1.1612198,
            1.3834949,
            1.6584899,
            1.9808633,
            2.3717519,
            2.8458587,
            3.4050773
          ],
          [
            0.0215804,
            0.0763921,
            0.0867595,
            0.0992032,
            0.1140375,
            0.1328931,
            0.1537902,
            0.1789623,
            0.2093424,
            0.2459368,
            0.2898503,
            0.3437912,
            0.4072348,
            0.4819931,
            0.572918,
            0.6818238,
            0.8127443,
            0.9722009,
            1.1591949,
            1.3851897,
            1.656518,
            1.9852255,
            2.3744748,
            2.8431526,
            3.4057133
          ],
          [
            0.0245145,
            0.0776954,
            0.0880628,
            0.1008856,
            0.1164027,
            0.1336813,
            0.15467,
            0.1800915,
            0.2110566,
            0.2478659,
            0.2914572,
            0.3440093,
            0.407152,
            0.4852813,
            0.5745009,
            0.6834902,
            0.8142977,
            0.9747385,
            1.1606828,
            1.3865823,
            1.6579657,
            1.9881401,
            2.3755709,
            2.8443721,
            3.4120071
          ],
          [
            0.0307495,
            0.0863413,
            0.0968818,
            0.1089544,
            0.1233338,
            0.1407767,
            0.1622616,
            0.1873092,
            0.2177323,
            0.2536382,
            0.2989938,
            0.3502203,
            0.4133134,
            0.4915097,
            0.5819341,
            0.6901297,
            0.820392,
            0.9805083,
            1.1663717,
            1.3946112,
            1.6653207,
            1.9904633,
            2.3811122,
            2.851009,
            3.4150947
          ],
          [
            0.0408798,
            0.1183649,
            0.1301125,
            0.1433599,
            0.1593591,
            0.176153,
            0.1958951,
            0.2199035,
            0.2490216,
            0.2846368,
            0.3272622,
            0.3797258,
            0.4411462,
            0.5160775,
            0.606338,
            0.7139098,
            0.8443239,
            1.0010852,
            1.1879256,
            1.4156569,
            1.6852362,
            2.0127113,
            2.4043911,
            2.8727012,
            3.4349688
          ],
          [
            0.0504589,
            0.1507324,
            0.1652571,
            0.1817884,
            0.200307,
            0.2216279,
            0.2456485,
            0.2733355,
            0.3040948,
            0.3413564,
            0.3821854,
            0.4315527,
            0.491221,
            0.564166,
            0.6516662,
            0.7581734,
            0.8860732,
            1.0392299,
            1.2249196,
            1.4522523,
            1.722368,
            2.0453734,
            2.437601,
            2.9050422,
            3.4667973
          ],
          [
            0.0640157,
            0.193442,
            0.2126546,
            0.2341851,
            0.2584906,
            0.2860392,
            0.3172577,
            0.3515521,
            0.3903766,
            0.4339842,
            0.4840318,
            0.5389953,
            0.6037798,
            0.6768358,
            0.7632584,
            0.8652162,
            0.9889836,
            1.1393051,
            1.3227918,
            1.5429146,
            1.8107457,
            2.129918,
            2.5162754,
            2.9844505,
            3.5397032
          ],
          [
            0.0743485,
            0.2254851,
            0.2471438,
            0.2728765,
            0.3004195,
            0.332346,
            0.3685867,
            0.4081952,
            0.4538602,
            0.5044206,
            0.5608414,
            0.626355,
            0.6989844,
            0.7818329,
            0.8736394,
            0.980634,
            1.1042334,
            1.2501239,
            1.4281251,
            1.6443994,
            1.9049378,
            2.2249842,
            2.6057014,
            3.0705423,
            3.6239742
          ],
          [
            0.0980491,
            0.2887511,
            0.3175141,
            0.349334,
            0.3849009,
            0.4257761,
            0.471566,
            0.5237666,
            0.5815066,
            0.6474467,
            0.7201966,
            0.8017223,
            0.8931642,
            0.9962742,
            1.1138092,
            1.2437485,
            1.3897271,
            1.5568525,
            1.7504128,
            1.9651227,
            2.2203479,
            2.5195592,
            2.8900637,
            3.3415051,
            3.8828913
          ],
          [
            0.1087438,
            0.3146163,
            0.3456419,
            0.3804992,
            0.4198244,
            0.4637261,
            0.5135738,
            0.5697432,
            0.6328808,
            0.7041377,
            0.7837678,
            0.873436,
            0.9727705,
            1.0843739,
            1.2109047,
            1.352633,
            1.5107453,
            1.690473,
            1.8930455,
            2.1234716,
            2.3889966,
            2.6931555,
            3.0576675,
            3.4952945,
            4.0370156
          ],
          [
            0.118979,
            0.3375509,
            0.3705469,
            0.4079502,
            0.4507867,
            0.4984013,
            0.5510752,
            0.6111817,
            0.6793036,
            0.7555998,
            0.8406232,
            0.9352663,
            1.0422391,
            1.1628855,
            1.2968311,
            1.4491573,
            1.6182219,
            1.8102299,
            2.022247,
            2.2658795,
            2.544895,
            2.8648826,
            3.230237,
            3.6645775,
            4.192628
          ]
        ]
      },
      "cell_rise,delay_template11x25": {
        "index_1": [
          0.001,
          0.013,
          0.026,
          0.072,
          0.216,
          0.432,
          0.864,
          1.296,
          2.5,
          3.125,
          3.75
        ],
        "index_2": [
          0,
          0.00986,
          0.01183,
          0.0142,
          0.01704,
          0.02045,
          0.02454,
          0.02945,
          0.03534,
          0.04241,
          0.05089,
          0.06107,
          0.07329,
          0.08795,
          0.10554,
          0.12665,
          0.15198,
          0.18238,
          0.21885,
          0.26262,
          0.31514,
          0.37817,
          0.4538,
          0.54456,
          0.65347
        ],
        "values": [
          [
            0.0123668,
            0.0609918,
            0.0696122,
            0.0799608,
            0.0923001,
            0.1069941,
            0.1250075,
            0.1461607,
            0.1704078,
            0.2014924,
            0.2370189,
            0.2804822,
            0.3333987,
            0.3960941,
            0.4690068,
            0.5600665,
            0.6676469,
            0.7976165,
            0.9521708,
            1.1370607,
            1.3647802,
            1.6347951,
            1.9547213,
            2.3374505,
            2.8067739
          ],
          [
            0.017649,
            0.0625921,
            0.0711767,
            0.0815235,
            0.0933115,
            0.1081937,
            0.1261964,
            0.1475418,
            0.1717522,
            0.2027801,
            0.2390812,
            0.283284,
            0.3349788,
            0.3964593,
            0.472232,
            0.5618981,
            0.67037,
            0.7991515,
            0.9535638,
            1.1429985,
            1.3681108,
            1.6359408,
            1.9549458,
            2.3394768,
            2.8094171
          ],
          [
            0.0212735,
            0.0648874,
            0.0734101,
            0.0838225,
            0.0959852,
            0.1104855,
            0.1281047,
            0.1494021,
            0.1749942,
            0.2056463,
            0.2404958,
            0.2850655,
            0.3366153,
            0.3986512,
            0.4742142,
            0.5647166,
            0.6723277,
            0.802155,
            0.9557445,
            1.1435543,
            1.3707933,
            1.6368454,
            1.9564221,
            2.3483713,
            2.8097478
          ],
          [
            0.0268635,
            0.075946,
            0.0842,
            0.0941205,
            0.1061867,
            0.1204402,
            0.1385438,
            0.1582538,
            0.1837709,
            0.2138513,
            0.2499967,
            0.2936978,
            0.34573,
            0.4085353,
            0.4823203,
            0.573257,
            0.6808092,
            0.8102565,
            0.9654646,
            1.1552599,
            1.3769818,
            1.6457324,
            1.9697413,
            2.3504247,
            2.8201073
          ],
          [
            0.0356093,
            0.1099846,
            0.1204079,
            0.1324112,
            0.14598,
            0.1614275,
            0.1786764,
            0.1979297,
            0.2213448,
            0.2503039,
            0.2853917,
            0.3278183,
            0.3784457,
            0.4397437,
            0.5143008,
            0.6036843,
            0.7106409,
            0.8403041,
            0.9948193,
            1.1839086,
            1.4072257,
            1.6746949,
            1.9911408,
            2.3819364,
            2.8433511
          ],
          [
            0.0410746,
            0.1397438,
            0.153668,
            0.1695862,
            0.1864435,
            0.2053984,
            0.2273384,
            0.252084,
            0.2799082,
            0.3120676,
            0.3479853,
            0.3896038,
            0.4384857,
            0.4980966,
            0.5699464,
            0.6579688,
            0.7631249,
            0.890587,
            1.0434905,
            1.2288275,
            1.4529132,
            1.7207878,
            2.0379451,
            2.4283595,
            2.8850975
          ],
          [
            0.0443579,
            0.1765378,
            0.1954913,
            0.2166534,
            0.2394844,
            0.2656713,
            0.2950072,
            0.3269484,
            0.3633668,
            0.4041442,
            0.4499526,
            0.500463,
            0.5578882,
            0.6234228,
            0.6982076,
            0.7817887,
            0.8839646,
            1.0080822,
            1.1560503,
            1.3398656,
            1.5612206,
            1.820744,
            2.1368245,
            2.5208799,
            2.9867924
          ],
          [
            0.0438882,
            0.1999293,
            0.2219069,
            0.2472398,
            0.275241,
            0.3059962,
            0.3406082,
            0.3794159,
            0.4220928,
            0.4700031,
            0.5237164,
            0.583281,
            0.6504257,
            0.7238451,
            0.8057488,
            0.9007134,
            1.0091571,
            1.1328474,
            1.2796163,
            1.4595307,
            1.6760744,
            1.9368032,
            2.2485633,
            2.6318638,
            3.0885421
          ],
          [
            0.0352175,
            0.2381187,
            0.2672138,
            0.3028065,
            0.337839,
            0.378842,
            0.4246313,
            0.4736214,
            0.5322005,
            0.5957137,
            0.667031,
            0.7456482,
            0.833279,
            0.9306423,
            1.0384326,
            1.1588819,
            1.2929735,
            1.4446183,
            1.6120776,
            1.8053734,
            2.0259472,
            2.2786426,
            2.5849181,
            2.9574689,
            3.4000192
          ],
          [
            0.029345,
            0.2512904,
            0.2827625,
            0.3187902,
            0.3588463,
            0.4045397,
            0.4549842,
            0.5102767,
            0.5736006,
            0.6427275,
            0.7207501,
            0.8079196,
            0.9036912,
            1.0112747,
            1.1306777,
            1.2626951,
            1.406815,
            1.5747085,
            1.7569868,
            1.9611028,
            2.1952757,
            2.462416,
            2.7670233,
            3.1348673,
            3.575692
          ],
          [
            0.0217433,
            0.2594416,
            0.294074,
            0.3333196,
            0.3771688,
            0.4273025,
            0.4813817,
            0.5419399,
            0.6057589,
            0.6841508,
            0.7675784,
            0.8603224,
            0.9644872,
            1.0802708,
            1.2053334,
            1.3495833,
            1.5115236,
            1.68692,
            1.8854636,
            2.1042095,
            2.3515969,
            2.6323963,
            2.9515401,
            3.3163514,
            3.7579468
          ]
        ]
      },
      "fall_transition,delay_template11x25": {
        "index_1": [
          0.001,
          0.013,
          0.026,
          0.072,
          0.216,
          0.432,
          0.864,
          1.296,
          2.5,
          3.125,
          3.75
        ],
        "index_2": [
          0,
          0.00986,
          0.01183,
          0.0142,
          0.01704,
          0.02045,
          0.02454,
          0.02945,
          0.03534,
          0.04241,
          0.05089,
          0.06107,
          0.07329,
          0.08795,
          0.10554,
          0.12665,
          0.15198,
          0.18238,
          0.21885,
          0.26262,
          0.31514,
          0.37817,
          0.4538,
          0.54456,
          0.65347
        ],
        "values": [
          [
            0.012144,
            0.0792604,
            0.0919642,
            0.1086862,
            0.1272778,
            0.1517258,
            0.1791238,
            0.2125915,
            0.2530289,
            0.3004328,
            0.3559723,
            0.4247795,
            0.5080255,
            0.6065169,
            0.7268466,
            0.868829,
            1.0397351,
            1.2428574,
            1.4911609,
            1.7906548,
            2.1390862,
            2.5632096,
            3.0818601,
            3.6964145,
            4.4256154
          ],
          [
            0.0121802,
            0.0793196,
            0.0928167,
            0.1085911,
            0.1285453,
            0.1517863,
            0.179267,
            0.2110796,
            0.2508687,
            0.2984942,
            0.3562366,
            0.4263342,
            0.5068596,
            0.605987,
            0.7269976,
            0.8692416,
            1.0393306,
            1.2428195,
            1.4896161,
            1.784049,
            2.1408215,
            2.5731342,
            3.076791,
            3.685747,
            4.4220041
          ],
          [
            0.0133094,
            0.0794418,
            0.0930543,
            0.1094272,
            0.1297151,
            0.150457,
            0.1780502,
            0.2114488,
            0.2522375,
            0.2985029,
            0.3561308,
            0.4243829,
            0.5079377,
            0.6066253,
            0.7247004,
            0.8694581,
            1.0396792,
            1.2455081,
            1.4882153,
            1.7837225,
            2.1440012,
            2.5718292,
            3.0742553,
            3.6888987,
            4.4275654
          ],
          [
            0.02561,
            0.0818196,
            0.0941941,
            0.1097347,
            0.129054,
            0.1519375,
            0.1803892,
            0.2117235,
            0.252671,
            0.2990775,
            0.356658,
            0.4251129,
            0.5076003,
            0.6108063,
            0.7279903,
            0.868816,
            1.0396122,
            1.2449053,
            1.4895819,
            1.7877542,
            2.1457762,
            2.5680527,
            3.0766061,
            3.6928793,
            4.4226138
          ],
          [
            0.0571194,
            0.1185116,
            0.1268983,
            0.1385563,
            0.1537279,
            0.1710375,
            0.194195,
            0.2228914,
            0.2585692,
            0.3025471,
            0.3583243,
            0.4252219,
            0.5092561,
            0.6063027,
            0.7261642,
            0.8684378,
            1.0412997,
            1.2433716,
            1.4929188,
            1.7853686,
            2.1487483,
            2.5718898,
            3.0808742,
            3.6952958,
            4.4255253
          ],
          [
            0.0952967,
            0.1792584,
            0.1896802,
            0.202322,
            0.2169087,
            0.2333598,
            0.253686,
            0.2760064,
            0.3058943,
            0.3446157,
            0.39115,
            0.4495507,
            0.5222453,
            0.6146478,
            0.7303627,
            0.8695469,
            1.0414236,
            1.2447081,
            1.4924708,
            1.7859549,
            2.1400219,
            2.5676219,
            3.0842109,
            3.6851222,
            4.4243609
          ],
          [
            0.1686882,
            0.2852324,
            0.298474,
            0.3151463,
            0.3334648,
            0.3536232,
            0.3765946,
            0.4029353,
            0.434192,
            0.4677259,
            0.5076187,
            0.5575877,
            0.6192623,
            0.6978784,
            0.7964336,
            0.9185168,
            1.0702337,
            1.2595687,
            1.4968699,
            1.7853464,
            2.1459854,
            2.5677567,
            3.0743992,
            3.6891117,
            4.4280246
          ],
          [
            0.2431809,
            0.3827455,
            0.3995645,
            0.4206144,
            0.4432401,
            0.4666316,
            0.4945661,
            0.5264134,
            0.5554873,
            0.5972799,
            0.6410771,
            0.6911151,
            0.7496844,
            0.8194583,
            0.902971,
            1.0124828,
            1.1488346,
            1.3193389,
            1.5458035,
            1.8123273,
            2.153989,
            2.5786209,
            3.081728,
            3.6937862,
            4.4298769
          ],
          [
            0.42601,
            0.6120424,
            0.6372006,
            0.6674831,
            0.6995325,
            0.7340098,
            0.7733749,
            0.8124375,
            0.8597811,
            0.9047146,
            0.9613528,
            1.0231479,
            1.0903231,
            1.1726733,
            1.2615851,
            1.3587035,
            1.4809967,
            1.6260223,
            1.8094466,
            2.0360593,
            2.3370015,
            2.7046596,
            3.1559777,
            3.7334287,
            4.447652
          ],
          [
            0.5331297,
            0.7287642,
            0.7576343,
            0.7884021,
            0.8220131,
            0.8600502,
            0.9027405,
            0.9519477,
            1.0036028,
            1.0636787,
            1.1188586,
            1.1883179,
            1.2653096,
            1.3482744,
            1.4408684,
            1.5446097,
            1.6693477,
            1.817254,
            1.988069,
            2.2024464,
            2.4731939,
            2.8259395,
            3.2668792,
            3.8076142,
            4.4907851
          ],
          [
            0.621604,
            0.8414343,
            0.8738663,
            0.9047672,
            0.9428475,
            0.98563,
            1.033769,
            1.0821245,
            1.134807,
            1.1998788,
            1.2669891,
            1.3413989,
            1.4277168,
            1.5139507,
            1.6165835,
            1.7272787,
            1.8528662,
            2.0024022,
            2.179537,
            2.3829534,
            2.6402105,
            2.9647338,
            3.3842815,
            3.9090438,
            4.5595825
          ]
        ]
      },
      "related_pin": "A",
      "rise_transition,delay_template11x25": {
        "index_1": [
          0.001,
          0.013,
          0.026,
          0.072,
          0.216,
          0.432,
          0.864,
          1.296,
          2.5,
          3.125,
          3.75
        ],
        "index_2": [
          0,
          0.00986,
          0.01183,
          0.0142,
          0.01704,
          0.02045,
          0.02454,
          0.02945,
          0.03534,
          0.04241,
          0.05089,
          0.06107,
          0.07329,
          0.08795,
          0.10554,
          0.12665,
          0.15198,
          0.18238,
          0.21885,
          0.26262,
          0.31514,
          0.37817,
          0.4538,
          0.54456,
          0.65347
        ],
        "values": [
          [
            0.0124819,
            0.0752202,
            0.0877899,
            0.1029537,
            0.1211451,
            0.1428835,
            0.1678071,
            0.1996185,
            0.2373913,
            0.2819468,
            0.3357757,
            0.400125,
            0.4769027,
            0.5701679,
            0.6819538,
            0.8156154,
            0.9758935,
            1.1690074,
            1.3987432,
            1.677804,
            2.0079665,
            2.4059099,
            2.8949783,
            3.4577212,
            4.1468575
          ],
          [
            0.0124941,
            0.0752143,
            0.0876332,
            0.1029397,
            0.120792,
            0.1422916,
            0.168574,
            0.2000287,
            0.237176,
            0.2814987,
            0.3363292,
            0.3994447,
            0.4771192,
            0.5697263,
            0.6817604,
            0.81661,
            0.9752922,
            1.1676362,
            1.4006188,
            1.6734829,
            2.0081257,
            2.4078013,
            2.8831721,
            3.4598779,
            4.1453028
          ],
          [
            0.0156394,
            0.0750665,
            0.0876407,
            0.102881,
            0.1207796,
            0.1423201,
            0.1685799,
            0.2001247,
            0.2371505,
            0.2811392,
            0.3356661,
            0.3999412,
            0.4774104,
            0.5691753,
            0.6820384,
            0.8155155,
            0.9763987,
            1.1686837,
            1.398199,
            1.6733508,
            2.0067135,
            2.4071329,
            2.8862266,
            3.4579579,
            4.1484305
          ],
          [
            0.0277561,
            0.0788919,
            0.0902823,
            0.1041776,
            0.1214463,
            0.1418721,
            0.1685064,
            0.1998316,
            0.2365891,
            0.2821013,
            0.335129,
            0.400642,
            0.4778049,
            0.5705351,
            0.6816233,
            0.8150939,
            0.9767573,
            1.1679043,
            1.3998489,
            1.6768229,
            2.009283,
            2.4069153,
            2.8842941,
            3.4593037,
            4.1458259
          ],
          [
            0.0557751,
            0.117647,
            0.1273059,
            0.1384442,
            0.1514302,
            0.168376,
            0.188903,
            0.2148506,
            0.2478659,
            0.2886861,
            0.3389788,
            0.401692,
            0.4774283,
            0.5696318,
            0.6811927,
            0.8161868,
            0.9753938,
            1.1686624,
            1.3983276,
            1.6764768,
            2.0087307,
            2.4088787,
            2.8857354,
            3.4541958,
            4.1471617
          ],
          [
            0.0901111,
            0.1740471,
            0.1851995,
            0.1967243,
            0.2107546,
            0.2288844,
            0.2490348,
            0.2721496,
            0.2995038,
            0.3342671,
            0.3754413,
            0.4320851,
            0.4986516,
            0.5840752,
            0.6889184,
            0.8186081,
            0.9749843,
            1.1660662,
            1.3996279,
            1.6764581,
            2.0091553,
            2.4059343,
            2.8862972,
            3.4584899,
            4.1496917
          ],
          [
            0.1555629,
            0.266938,
            0.281512,
            0.2977485,
            0.3192698,
            0.3399506,
            0.3630149,
            0.3888129,
            0.4159593,
            0.4546324,
            0.4947465,
            0.539568,
            0.5969999,
            0.6711098,
            0.7621496,
            0.876228,
            1.0169707,
            1.1945863,
            1.4119506,
            1.6807372,
            2.0068478,
            2.4042821,
            2.886281,
            3.4569445,
            4.1497734
          ],
          [
            0.2194968,
            0.3504608,
            0.3671648,
            0.3862759,
            0.4099426,
            0.433863,
            0.4670944,
            0.4966083,
            0.5311555,
            0.5679183,
            0.6096298,
            0.659567,
            0.7168781,
            0.7860467,
            0.8731069,
            0.9735653,
            1.1050901,
            1.2657901,
            1.4694271,
            1.7219919,
            2.0326512,
            2.4115294,
            2.8877498,
            3.4585761,
            4.146822
          ],
          [
            0.4048681,
            0.5496917,
            0.5751011,
            0.6055027,
            0.6319185,
            0.6682663,
            0.7074963,
            0.7583917,
            0.7985414,
            0.849703,
            0.9045357,
            0.967326,
            1.0356409,
            1.1118435,
            1.206731,
            1.3008968,
            1.4255671,
            1.5644149,
            1.7459804,
            1.9602466,
            2.2320059,
            2.5763476,
            3.0071829,
            3.5257051,
            4.1817922
          ],
          [
            0.5033379,
            0.6429942,
            0.673218,
            0.7044472,
            0.7385,
            0.7795933,
            0.8225141,
            0.8695607,
            0.9230416,
            0.9844406,
            1.0463123,
            1.1153799,
            1.1895585,
            1.2722911,
            1.3721703,
            1.4758138,
            1.593349,
            1.7409809,
            1.9097055,
            2.1229494,
            2.3791284,
            2.7020373,
            3.1098053,
            3.6189634,
            4.2471986
          ],
          [
            0.6027086,
            0.7389366,
            0.7691823,
            0.7999221,
            0.8378696,
            0.8852858,
            0.9328859,
            0.9849827,
            1.0414773,
            1.103531,
            1.1723872,
            1.2489175,
            1.3332123,
            1.4308552,
            1.5305852,
            1.6417674,
            1.7678968,
            1.9132,
            2.0846176,
            2.2877635,
            2.540677,
            2.8486609,
            3.259695,
            3.7255807,
            4.340611
          ]
        ]
      },
      "timing_sense": "negative_unate"
    }
  }
}